LICENSE
MANIFEST.in
README.md
setup.cfg
setup.py
build_capi/__init__.py
build_capi/_unicode.py
build_capi/build.py
build_capi/ext.py
build_capi.egg-info/PKG-INFO
build_capi.egg-info/SOURCES.txt
build_capi.egg-info/dependency_links.txt
build_capi.egg-info/entry_points.txt
build_capi.egg-info/not-zip-safe
build_capi.egg-info/top_level.txt