Metadata-Version: 1.1
Name: build-capi
Version: 1.1.9
Summary: Build and distribute C/C++ static libraries
Home-page: http://github.com/Horta/build-capi
Author: Danilo Horta
Author-email: horta@ebi.ac.uk
License: MIT
Platform: UNKNOWN
Classifier: Development Status :: 5 - Production/Stable
Classifier: Intended Audience :: Developers
Classifier: License :: OSI Approved :: MIT License
Classifier: Programming Language :: Python :: 2.7
Classifier: Programming Language :: Python :: 3.4
Classifier: Programming Language :: Python :: 3.5
Classifier: Operating System :: OS Independent
